{
  "Thu.000": "Dette stedet er fullt av minner for meg. Tusen takk for at du har restaurert det.$h",
  "2.001": "Å kjære, er det en nødsituasjon? Hvorfor er du her?$s",
  "winter_17.000": "Dette er en av de nyere tradisjonene i Pelican Town... men vi har tatt det til oss ganske raskt. Ikke sant, George?",
  "23.000": "Rolig nå, kjære... Det er viktig at doktor Harvey tar en god titt på deg. Han er en hyggelig ung mann! Oppfør deg, for din kjære gamle kones skyld.",
  "23.001": "Kan du sjekke lungene hans? Han har hveset i det siste.",
  "2.000": "Når du kommer i min alder, må du gå til legen oftere."
}